freezerclient/__init__.py
freezerclient/client.py
freezerclient/exceptions.py
freezerclient/shell.py
freezerclient/utils.py
freezerclient/tests/__init__.py
freezerclient/tests/unit/__init__.py
freezerclient/tests/unit/test_client.py
freezerclient/tests/unit/test_exceptions.py
freezerclient/tests/unit/test_shell.py
freezerclient/tests/unit/test_utils.py
freezerclient/tests/unit/v1/__init__.py
freezerclient/tests/unit/v1/test_client.py
freezerclient/tests/unit/v1/test_client_actions.py
freezerclient/tests/unit/v1/test_client_backups.py
freezerclient/tests/unit/v1/test_client_clients.py
freezerclient/tests/unit/v1/test_client_jobs.py
freezerclient/tests/unit/v1/test_client_sessions.py
freezerclient/tests/unit/v2/__init__.py
freezerclient/tests/unit/v2/test_client.py
freezerclient/tests/unit/v2/test_client_actions.py
freezerclient/tests/unit/v2/test_client_backups.py
freezerclient/tests/unit/v2/test_client_clients.py
freezerclient/tests/unit/v2/test_client_jobs.py
freezerclient/tests/unit/v2/test_client_sessions.py
freezerclient/v1/__init__.py
freezerclient/v1/actions.py
freezerclient/v1/backups.py
freezerclient/v1/client.py
freezerclient/v1/clients.py
freezerclient/v1/jobs.py
freezerclient/v1/sessions.py
freezerclient/v1/managers/__init__.py
freezerclient/v1/managers/actions.py
freezerclient/v1/managers/backups.py
freezerclient/v1/managers/clients.py
freezerclient/v1/managers/jobs.py
freezerclient/v1/managers/sessions.py
freezerclient/v2/__init__.py
freezerclient/v2/actions.py
freezerclient/v2/backups.py
freezerclient/v2/client.py
freezerclient/v2/clients.py
freezerclient/v2/jobs.py
freezerclient/v2/sessions.py
freezerclient/v2/managers/__init__.py
freezerclient/v2/managers/actions.py
freezerclient/v2/managers/backups.py
freezerclient/v2/managers/clients.py
freezerclient/v2/managers/jobs.py
freezerclient/v2/managers/sessions.py
python_freezerclient-6.1.0.dist-info/AUTHORS
python_freezerclient-6.1.0.dist-info/LICENSE
python_freezerclient-6.1.0.dist-info/METADATA
python_freezerclient-6.1.0.dist-info/WHEEL
python_freezerclient-6.1.0.dist-info/entry_points.txt
python_freezerclient-6.1.0.dist-info/pbr.json
python_freezerclient-6.1.0.dist-info/top_level.txt
python_freezerclient-6.1.0.dist-info/RECORD
