Metadata-Version: 2.1
Name: python-freezerclient
Version: 6.1.0
Summary: OpenStack Disaster Recovery API Client Library
Home-page: https://docs.openstack.org/python-freezerclient/latest/
Author: OpenStack
Author-email: openstack-discuss@lists.openstack.org
License: Apache License, Version 2.0
Keywords: freezer,freezerclient,python-freezerclient
Classifier: Programming Language :: Python
Classifier: Programming Language :: Python :: Implementation :: CPython
Classifier: Programming Language :: Python :: 3 :: Only
Classifier: Programming Language :: Python :: 3
Classifier: Programming Language :: Python :: 3.8
Classifier: Programming Language :: Python :: 3.9
Classifier: Programming Language :: Python :: 3.10
Classifier: Programming Language :: Python :: 3.11
Classifier: Programming Language :: Python :: 3.12
Classifier: Development Status :: 5 - Production/Stable
Classifier: Natural Language :: English
Classifier: Environment :: OpenStack
Classifier: Intended Audience :: Developers
Classifier: Intended Audience :: Information Technology
Classifier: Intended Audience :: System Administrators
Classifier: License :: OSI Approved :: Apache Software License
Classifier: Operating System :: MacOS
Classifier: Operating System :: POSIX :: BSD :: FreeBSD
Classifier: Operating System :: POSIX :: BSD :: NetBSD
Classifier: Operating System :: POSIX :: BSD :: OpenBSD
Classifier: Operating System :: POSIX :: Linux
Classifier: Operating System :: Microsoft :: Windows
Classifier: Operating System :: Unix
Classifier: Topic :: System :: Archiving :: Backup
Classifier: Topic :: System :: Archiving :: Compression
Classifier: Topic :: System :: Archiving
Requires-Python: >=3.8
License-File: LICENSE
License-File: AUTHORS
Requires-Dist: setuptools !=24.0.0,!=34.0.0,!=34.0.1,!=34.0.2,!=34.0.3,!=34.1.0,!=34.1.1,!=34.2.0,!=34.3.0,!=34.3.1,!=34.3.2,!=36.2.0,>=21.0.0
Requires-Dist: pbr !=2.1.0,>=2.0.0
Requires-Dist: keystoneauth1 >=3.4.0
Requires-Dist: cliff !=2.9.0,>=2.8.0
Requires-Dist: oslo.serialization >=2.25.0
Requires-Dist: oslo.utils >=3.33.0
